versionah/__init__.py
versionah/_version.py
versionah/cmdline.py
versionah/models.py
versionah/locale/versionah.pot
versionah/templates/c.jinja
versionah/templates/go.jinja
versionah/templates/h.jinja
versionah/templates/json.jinja
versionah/templates/lua.jinja
versionah/templates/m4.jinja
versionah/templates/moon.jinja
versionah/templates/py.jinja
versionah/templates/rb.jinja
versionah/templates/text.jinja
versionah-0.16.0.dist-info/DESCRIPTION.rst
versionah-0.16.0.dist-info/METADATA
versionah-0.16.0.dist-info/RECORD
versionah-0.16.0.dist-info/WHEEL
versionah-0.16.0.dist-info/entry_points.txt
versionah-0.16.0.dist-info/metadata.json
versionah-0.16.0.dist-info/top_level.txt
